pooetry/main.py
pooetry-0.1.3.dist-info/entry_points.txt
pooetry-0.1.3.dist-info/WHEEL
pooetry-0.1.3.dist-info/METADATA
pooetry-0.1.3.dist-info/RECORD
