Metadata-Version: 2.1
Name: pooetry
Version: 0.1.3
Summary: An almost-useless wrapper for the great packaging tool poetry
Home-page: https://github.com/ChrisArgyle/pooetry
License: MIT
Author: ChrisArgyle
Author-email: chrisisdiy@gmail.com
Requires-Python: >=3.6,<4.0
Classifier: License :: OSI Approved :: MIT License
Classifier: Programming Language :: Python :: 3
Classifier: Programming Language :: Python :: 3.6
Classifier: Programming Language :: Python :: 3.7
Requires-Dist: rfc3986 (>=1.3,<2.0)
Project-URL: Repository, https://github.com/ChrisArgyle/pooetry
